{"enableComments":false,"objectRelationships":[],"enableObjectEntryVersioning":false,"objectFolderExternalReferenceCode":"d575841a-8b36-9c09-492a-c97be1deebae","enableCategorization":true,"enableFriendlyURLCustomization":false,"accountEntryRestrictedObjectFieldName":"","className":"com.liferay.object.model.ObjectDefinition#Q3Y1","objectActions":[],"enableLocalization":true,"accountEntryRestricted":false,"enableFormContainer":true,"enableObjectEntrySubscription":false,"externalReferenceCode":"4106d587-9711-e9e1-26d6-391e09d4a34d","workflowDefinitionLinks":[],"objectFields":[{"indexed":false,"defaultValue":"null","localized":false,"objectFieldSettings":[],"readOnly":"true","DBType":"String","label":{"en_US":"Author"},"type":"String","required":false,"externalReferenceCode":"ad492a1e-94f3-5fc7-96fd-7b5eb838330c","indexedAsKeyword":false,"system":true,"indexedLanguageId":"","unique":false,"name":"creator","state":false,"businessType":"Text","readOnlyConditionExpression":""},{"indexed":false,"defaultValue":"null","localized":false,"objectFieldSettings":[],"readOnly":"true","DBType":"Date","label":{"en_US":"Create Date"},"type":"Date","required":false,"externalReferenceCode":"b20e5610-feb6-2554-22f3-96856b2f0fb9","indexedAsKeyword":false,"system":true,"indexedLanguageId":"","unique":false,"name":"createDate","state":false,"businessType":"Date","readOnlyConditionExpression":""},{"indexed":false,"defaultValue":"null","localized":false,"objectFieldSettings":[],"readOnly":"false","DBType":"String","label":{"en_US":"External Reference Code"},"type":"String","required":false,"externalReferenceCode":"30ef1add-f140-a892-fd8a-ed21680a0545","indexedAsKeyword":false,"system":true,"indexedLanguageId":"","unique":false,"name":"externalReferenceCode","state":false,"businessType":"Text","readOnlyConditionExpression":""},{"indexed":false,"defaultValue":"null","localized":false,"objectFieldSettings":[{"name":"timeStorage","value":"convertToUTC"}],"readOnly":"false","DBType":"DateTime","label":{"en_US":"Display Date"},"type":"DateTime","required":false,"externalReferenceCode":"ef2bf9e4-5dec-3bb4-c084-cd11354a4ece","indexedAsKeyword":false,"system":true,"indexedLanguageId":"","unique":false,"name":"displayDate","state":false,"businessType":"DateTime","readOnlyConditionExpression":""},{"indexed":false,"defaultValue":"null","localized":false,"objectFieldSettings":[{"name":"timeStorage","value":"convertToUTC"}],"readOnly":"false","DBType":"DateTime","label":{"en_US":"Expiration Date"},"type":"DateTime","required":false,"externalReferenceCode":"ca394cfc-e8ea-62f2-d3aa-9a000f1f3d99","indexedAsKeyword":false,"system":true,"indexedLanguageId":"","unique":false,"name":"expirationDate","state":false,"businessType":"DateTime","readOnlyConditionExpression":""},{"indexed":false,"defaultValue":"null","localized":false,"objectFieldSettings":[{"name":"timeStorage","value":"convertToUTC"}],"readOnly":"false","DBType":"DateTime","label":{"en_US":"Review Date"},"type":"DateTime","required":false,"externalReferenceCode":"100d3bfd-568d-b02b-c2d8-2dde0d43dfe1","indexedAsKeyword":false,"system":true,"indexedLanguageId":"","unique":false,"name":"reviewDate","state":false,"businessType":"DateTime","readOnlyConditionExpression":""},{"indexed":true,"defaultValue":"null","localized":false,"objectFieldSettings":[],"readOnly":"true","DBType":"Long","label":{"en_US":"ID"},"type":"Long","required":false,"externalReferenceCode":"7ad848e8-7bac-4414-bc02-147b0e7e5320","indexedAsKeyword":true,"system":true,"indexedLanguageId":"","unique":false,"name":"id","state":false,"businessType":"LongInteger","readOnlyConditionExpression":""},{"indexed":false,"defaultValue":"null","localized":false,"objectFieldSettings":[],"readOnly":"true","DBType":"Date","label":{"en_US":"Modified Date"},"type":"Date","required":false,"externalReferenceCode":"ede73bb0-c14f-4a9b-0347-af83dd5a9769","indexedAsKeyword":false,"system":true,"indexedLanguageId":"","unique":false,"name":"modifiedDate","state":false,"businessType":"Date","readOnlyConditionExpression":""},{"indexed":false,"defaultValue":"null","localized":false,"objectFieldSettings":[],"readOnly":"true","DBType":"Integer","label":{"en_US":"Status"},"type":"Integer","required":false,"externalReferenceCode":"2a26868c-817a-aa71-1695-1ff8ecfe8183","indexedAsKeyword":false,"system":true,"indexedLanguageId":"","unique":false,"name":"status","state":false,"businessType":"Text","readOnlyConditionExpression":""},{"indexed":true,"defaultValue":"null","localized":false,"objectFieldSettings":[{"name":"showCounter","value":false}],"readOnly":"false","DBType":"String","label":{"en_US":"Store name"},"type":"String","required":false,"externalReferenceCode":"01c347dc-7171-c336-2999-f36998f7deb5","indexedAsKeyword":false,"system":false,"indexedLanguageId":"en_US","unique":false,"name":"storeName","state":false,"businessType":"Text","readOnlyConditionExpression":""},{"indexed":true,"defaultValue":"null","localized":false,"objectFieldSettings":[{"name":"showCounter","value":false}],"readOnly":"false","DBType":"String","label":{"en_US":"Street Address 1"},"type":"String","required":false,"externalReferenceCode":"afde59a7-b88b-892d-19c9-fa7d13f5f386","indexedAsKeyword":false,"system":false,"indexedLanguageId":"en_US","unique":false,"name":"streetAddress1","state":false,"businessType":"Text","readOnlyConditionExpression":""},{"indexed":true,"defaultValue":"null","localized":false,"objectFieldSettings":[{"name":"showCounter","value":false}],"readOnly":"false","DBType":"String","label":{"en_US":"Street Address 2"},"type":"String","required":false,"externalReferenceCode":"7951892d-2b0c-d43c-e382-a63936b86e96","indexedAsKeyword":false,"system":false,"indexedLanguageId":"en_US","unique":false,"name":"streetAddress2","state":false,"businessType":"Text","readOnlyConditionExpression":""},{"indexed":true,"defaultValue":"null","localized":false,"objectFieldSettings":[{"name":"showCounter","value":false}],"readOnly":"false","DBType":"String","label":{"en_US":"City"},"type":"String","required":false,"externalReferenceCode":"e1e64ec9-f5d6-493a-2511-7dc941c92cde","indexedAsKeyword":false,"system":false,"indexedLanguageId":"en_US","unique":false,"name":"city","state":false,"businessType":"Text","readOnlyConditionExpression":""},{"indexed":true,"defaultValue":"null","localized":false,"objectFieldSettings":[{"name":"showCounter","value":false}],"readOnly":"false","DBType":"String","label":{"en_US":"State Province Region"},"type":"String","required":false,"externalReferenceCode":"aa939370-4378-1be4-3139-26e573206c95","indexedAsKeyword":false,"system":false,"indexedLanguageId":"en_US","unique":false,"name":"stateProvinceRegion","state":false,"businessType":"Text","readOnlyConditionExpression":""},{"indexed":true,"defaultValue":"null","localized":false,"objectFieldSettings":[{"name":"showCounter","value":false}],"readOnly":"false","DBType":"String","label":{"en_US":"Postal zip code"},"type":"String","required":false,"externalReferenceCode":"1c476986-a6dd-b4da-b9cc-0005ba0f977d","indexedAsKeyword":false,"system":false,"indexedLanguageId":"en_US","unique":false,"name":"postalZipCode","state":false,"businessType":"Text","readOnlyConditionExpression":""},{"indexed":true,"defaultValue":"null","localized":false,"objectFieldSettings":[{"name":"showCounter","value":false}],"readOnly":"false","DBType":"String","label":{"en_US":"Country"},"type":"String","required":false,"externalReferenceCode":"4170f6af-1255-f584-4fea-9c29ffac8f7f","indexedAsKeyword":false,"system":false,"indexedLanguageId":"en_US","unique":false,"name":"country","state":false,"businessType":"Text","readOnlyConditionExpression":""},{"indexed":true,"defaultValue":"null","localized":false,"objectFieldSettings":[],"readOnly":"false","DBType":"Double","label":{"en_US":"Latitude"},"type":"Double","required":false,"externalReferenceCode":"e913d47a-b024-99a0-3fe5-ce589b200bd2","indexedAsKeyword":false,"system":false,"indexedLanguageId":"","unique":false,"name":"latitude","state":false,"businessType":"Decimal","readOnlyConditionExpression":""},{"indexed":true,"defaultValue":"null","localized":false,"objectFieldSettings":[],"readOnly":"false","DBType":"Double","label":{"en_US":"Longitude"},"type":"Double","required":false,"externalReferenceCode":"cf85d878-ad31-ba75-153a-cfa762c161e9","indexedAsKeyword":false,"system":false,"indexedLanguageId":"","unique":false,"name":"longitude","state":false,"businessType":"Decimal","readOnlyConditionExpression":""},{"indexed":true,"defaultValue":"null","localized":false,"objectFieldSettings":[{"name":"showCounter","value":false}],"readOnly":"false","DBType":"String","label":{"en_US":"Phone Number"},"type":"String","required":false,"externalReferenceCode":"25bae3b8-0ab9-c6af-c35e-3730e80c2204","indexedAsKeyword":false,"system":false,"indexedLanguageId":"en_US","unique":false,"name":"phoneNumber","state":false,"businessType":"Text","readOnlyConditionExpression":""}],"restContextPath":"/o/c/distributors","scope":"company","portlet":true,"friendlyURLSeparator":"c_distributor","modifiable":true,"parameterRequired":false,"enableObjectEntryHistory":false,"creator":{"image":"/image/user_portrait?img_id=36295&img_id_token=FDzzK00xpUhqppFv7%2FDeFHn37Iw%3D&t=1780330210690","familyName":"Test","givenName":"Test","name":"Test Test","additionalName":"","contentType":"UserAccount","externalReferenceCode":"de4ef19d-8105-f1c3-3b4e-3eedbd051a02"},"titleObjectFieldName":"storeName","objectValidationRules":[],"active":true,"defaultLanguageId":"en_US","enableIndexSearch":true,"label":{"en_US":"Distributor"},"panelCategoryKey":"control_panel.account_entries_admin","pluralLabel":{"en_US":"Distributors"},"enableObjectEntrySchedule":false,"objectLayouts":[],"system":false,"objectDefinitionSettings":[],"objectViews":[],"enableObjectEntryDraft":false,"name":"Distributor","storageType":"default","actions":{"permissions":{},"get":{},"update":{},"delete":{},"exportObjectDefinition":{}},"status":{"label_i18n":"Approved","code":0,"label":"approved"}}